undetected_chromedriver/__init__.py
undetected_chromedriver/cdp.py
undetected_chromedriver/devtool.py
undetected_chromedriver/dprocess.py
undetected_chromedriver/options.py
undetected_chromedriver/patcher.py
undetected_chromedriver/reactor.py
undetected_chromedriver/webelement.py
undetected_chromedriver2/__init__.py
undetected_chromedriver2/cdp.py
undetected_chromedriver2/devtool.py
undetected_chromedriver2/dprocess.py
undetected_chromedriver2/options.py
undetected_chromedriver2/patcher.py
undetected_chromedriver2/reactor.py
undetected_chromedriver2/webelement.py
undetected_chromedriver2-3.5.1.dist-info/LICENSE
undetected_chromedriver2-3.5.1.dist-info/METADATA
undetected_chromedriver2-3.5.1.dist-info/WHEEL
undetected_chromedriver2-3.5.1.dist-info/top_level.txt
undetected_chromedriver2-3.5.1.dist-info/RECORD
